downloads_sorter/__init__.py
downloads_sorter/cli.py
downloads_sorter/sorter.py
downloads_sorter-0.2.1.dist-info/licenses/LICENSE
downloads_sorter-0.2.1.dist-info/METADATA
downloads_sorter-0.2.1.dist-info/WHEEL
downloads_sorter-0.2.1.dist-info/entry_points.txt
downloads_sorter-0.2.1.dist-info/top_level.txt
downloads_sorter-0.2.1.dist-info/RECORD
