Metadata-Version: 2.4
Name: downloads-sorter
Version: 0.2.1
Summary: A powerful tool to automatically organize your downloads folder
Author: Olivier Dobberkau
License-Expression: MIT
Project-URL: Homepage, https://dkd-dobberkau.github.io/downloads-sorter/
Project-URL: Repository, https://github.com/dkd-dobberkau/downloads-sorter
Project-URL: Issues, https://github.com/dkd-dobberkau/downloads-sorter/issues
Project-URL: Documentation, https://dkd-dobberkau.github.io/downloads-sorter/
Keywords: downloads,file organization,utility,cli,automation
Classifier: Development Status :: 4 - Beta
Classifier: Environment :: Console
Classifier: Intended Audience :: End Users/Desktop
Classifier: Operating System :: OS Independent
Classifier: Programming Language :: Python :: 3
Classifier: Programming Language :: Python :: 3.8
Classifier: Programming Language :: Python :: 3.9
Classifier: Programming Language :: Python :: 3.10
Classifier: Programming Language :: Python :: 3.11
Classifier: Programming Language :: Python :: 3.12
Classifier: Topic :: Desktop Environment :: File Managers
Classifier: Topic :: Utilities
Requires-Python: >=3.8
License-File: LICENSE
Dynamic: license-file
